dayu_widgets_overlay/__init__.py
dayu_widgets_overlay/__version__.py
dayu_widgets_overlay/overlay.py
dayu_widgets_overlay-0.1.1.dist-info/LICENSE
dayu_widgets_overlay-0.1.1.dist-info/WHEEL
dayu_widgets_overlay-0.1.1.dist-info/METADATA
dayu_widgets_overlay-0.1.1.dist-info/RECORD
