Metadata-Version: 2.1
Name: dayu-widgets-overlay
Version: 0.1.1
Summary: dayu_widgets MOverlay Widget for QtDesigner
License: MIT
Keywords: PySide,PyQt,UI,PySide2,PyQt5,dayu_widgets
Author: timmyliang
Author-email: 820472580@qq.com
Requires-Python: >=2.7, !=3.0.*, !=3.1.*, !=3.2.*, !=3.3.*, !=3.4.*, !=3.5.*
Classifier: License :: OSI Approved :: MIT License
Classifier: Programming Language :: Python :: 2
Classifier: Programming Language :: Python :: 2.7
Classifier: Programming Language :: Python :: 3
Classifier: Programming Language :: Python :: 3.5
Classifier: Programming Language :: Python :: 3.6
Classifier: Programming Language :: Python :: 3.7
Classifier: Programming Language :: Python :: 3.8
Classifier: Programming Language :: Python :: 3.9
Requires-Dist: Qt.py (>=1.3.6,<2.0.0)
Requires-Dist: dayu-path (>=0.5.2,<0.6.0)
Requires-Dist: singledispatch (>=3.7.0,<4.0.0); python_version == "2.7"
Requires-Dist: six (>=1.16.0,<2.0.0)
